{
    "CRAB": {
        "name": "Crab",
        "maxHp": 50,
        "ai.idleMin": 4.0,
        "ai.idleMax": 8.0,
        "ai.idleSeekDistance": 48.0,
        "ai.strollMin": 3.0,
        "ai.strollMax": 6.0,
        "ai.strollSpeed": 8.0,
        "ai.strollSeekDistance": 48.0,
        "ai.fleeMin": 5.0,
        "ai.fleeMax": 8.0,
        "ai.fleeSpeed": 16.0,
        "ai.chaseDistance": 64.0,
        "ai.chaseSpeed": 16.0,
        "ai.attackDistance": 16.0,
        "ai.attackCooldown": 1.5,
        "ai.attackDuration": 0.64,
        "ai.attackDamage": 10.0,
        "ai.attackAt": 0.40,
        "ai.attackRange": 20.0,
        "ai.seekTargets": ["PLAYER", "CHICKEN"]
    },
    "ZOMBIE": {
        "name": "Zombie",
        "maxHp": 100,
        "ai.idleMin": 4.0,
        "ai.idleMax": 8.0,
        "ai.idleSeekDistance": 96.0,
        "ai.strollMin": 3.0,
        "ai.strollMax": 6.0,
        "ai.strollSpeed": 24.0,
        "ai.strollSeekDistance": 112.0,
        "ai.chaseDistance": 64.0,
        "ai.chaseSpeed": 32.0,
        "ai.attackDistance": 16.0,
        "ai.attackCooldown": 1.5,
        "ai.attackDuration": 0.5,
        "ai.attackDamage": 20.0,
        "ai.attackAt": 0.25,
        "ai.attackRange": 16.0
    },
    "WOODFOLK": {
        "name": "Woodfolk",
        "maxHp": 60,
        "ai.idleMin": 1.0,
        "ai.idleMax": 3.0,
        "ai.idleSeekDistance": 120.0,
        "ai.strollMin": 3.0,
        "ai.strollMax": 6.0,
        "ai.strollSpeed": 12.0,
        "ai.strollSeekDistance": 132.0,
        "ai.chaseDistance": 148.0,
        "ai.chaseSpeed": 36.0,
        "ai.attackDistance": 8.0,
        "ai.attackCooldown": 1.0,
        "ai.attackDuration": 0.2,
        "ai.attackDamage": 12.0,
        "ai.attackAt": 0.125,
        "ai.attackRange": 8.0
    },
    "SLIME": {
        "name": "Slime",
        "maxHp": 60,
        "ai.idleMin": 1.0,
        "ai.idleMax": 3.0,
        "ai.idleSeekDistance": 120.0,
        "ai.strollMin": 3.0,
        "ai.strollMax": 6.0,
        "ai.strollSpeed": 12.0,
        "ai.strollSeekDistance": 132.0,
        "ai.chaseDistance": 148.0,
        "ai.attackDistance": 8.0,
        "ai.attackCooldown": 1.0,
        "ai.attackDuration": 0.2,
        "ai.attackDamage": 12.0,
        "ai.attackAt": 0.125,
        "ai.attackRange": 8.0,
        "ai.hopDuration": 0.6,
        "ai.hopSpeed": 24.0,
        "ai.hopDelay": 0.25,
        "ai.hopMin": 2,
        "ai.hopMax": 4,
        "ai.hopSeekDistance": 132.0,
        "ai.chaseHopDuration": 0.6,
        "ai.chaseHopDelay": 0.05,
        "ai.chaseSpeed": 24.0
    },
    "PLAYER": {
        "maxHp": 100,
        "healthBar.offsetY": 8.0
    },
    "CHICKEN": {
        "name": "Chicken",
        "maxHp": 40,
        "ai.idleMin": 1.0,
        "ai.idleMax": 3.0,
        "ai.strollMin": 1.0,
        "ai.strollMax": 3.0,
        "ai.strollSpeed": 12.0,
        "ai.fleeMin": 6.0,
        "ai.fleeMax": 8.0,
        "ai.fleeSpeed": 32.0
    },
    "WORM": {
        "name": "Worm",
        "maxHp": 20,
        "ai.idleMin": 1.0,
        "ai.idleMax": 3.0,
        "ai.strollMin": 1.0,
        "ai.strollMax": 3.0,
        "ai.strollSpeed": 5.0,
        "ai.fleeMin": 6.0,
        "ai.fleeMax": 8.0,
        "ai.fleeSpeed": 8.0
    },
    "MAGGOT": {
        "name": "Maggot",
        "maxHp": 30,
        "ai.idleMin": 1.0,
        "ai.idleMax": 3.0,
        "ai.strollMin": 1.0,
        "ai.strollMax": 3.0,
        "ai.strollSpeed": 5.0,
        "ai.fleeMin": 6.0,
        "ai.fleeMax": 8.0,
        "ai.fleeSpeed": 8.0
    },
    "FIREFLY": {
        "name": "Firefly",
        "maxHp": 20,
        "ai.idleMin": 0.000,
        "ai.idleMax": 0.001,
        "ai.strollMin": 0.4,
        "ai.strollMax": 0.6,
        "ai.strollSpeed": 40.0,
        "ai.fleeMin": 6.0,
        "ai.fleeMax": 8.0,
        "ai.fleeSpeed": 48.0,
        "healthBar.offsetY": 16.0
    },
    "GRASS": {
        "bbox.population": [-4.0, 0, 8, 7]
    },
    "MUSHROOM_RED": {
        "bbox.population": [-4.0, 0, 8, 7]
    },
    "MUSHROOM_BROWN": {
        "bbox.population": [-4.0, 0, 8, 7]
    },
    "MUSHROOM_GLOWING": {
        "bbox.population": [-4.0, 0, 8, 7]
    },
    "BLUEBERRY_BUSH": {
        "bbox.population": [-7.5, 0, 15, 13]
    },
    "ROCK": {
        "bbox.population": [-5.0, 0, 10, 10]
    },
    "SUNFLOWER": {
        "bbox.population": [-5.0, 0, 10, 9]
    },
    "LILYPAD": {
        "bbox.population": [-5.0, 0, 10, 8]
    },
    "OAK_TREE": {
        "bbox.population": [-15.0, -4, 31, 16],
        "maxHp.var1": 120.0,
        "maxHp.var2": 120.0,
        "maxHp.var3": 150.0,
        "maxHp.var4": 150.0,
        "maxHp.var5": 180.0,
        "maxHp.var6": 180.0,
        "maxHp.trunk": 30.0,
        "name.var1": "Small Oak Tree",
        "name.var2": "Small Oak Tree",
        "name.var3": "Medium Oak Tree",
        "name.var4": "Medium Oak Tree",
        "name.var5": "Large Oak Tree",
        "name.var6": "Large Oak Tree",
        "name.trunk": "Oak Tree Trunk"
    },
    "CATTAIL": {
        "bbox.population": [-6.0, 0, 12.0, 8.0]
    },
    "CAMPFIRE": {
        "bbox.population": [-5.0, 0, 10.0, 12.0]
    },
    "ALOE_VERA": {
        "bbox.population": [-11.0, 0, 22.0, 14.0]
    },
    "BUSH": {
        "bbox.population": [-8.0, 0, 16, 12],
        "maxHp": 40.0,
        "name": "Bush"
    },
    "BOULDER": {
        "bbox.population": [-8.0, 0, 16, 10],
        "maxHp.var1": 75.0,
        "maxHp.var2": 90.0,
        "name.var1": "Boulder",
        "name.var2": "Coal Boulder"
    },
    "DYNAMIC_3D_TILE": {
        "bbox.population": [0, 0, 16.0, 16.0],
        "maxHp.DIRT": 75.0,
        "maxHp.ROCK": 75.0,
        "maxHp.OAKPLANKWALL": 75.0,
        "name.DIRT": "Dirt Wall",
        "name.ROCK": "Rock Wall",
        "name.OAKPLANKWALL": "Oak Plank Wall"
    }
}